coopstarter_data/__init__.py
coopstarter_data/admin.py
coopstarter_data/apps.py
coopstarter_data/context_processors.py
coopstarter_data/djangoldp_urls.py
coopstarter_data/filters.py
coopstarter_data/middleware.py
coopstarter_data/models.py
coopstarter_data/permissions.py
coopstarter_data/settings.py
coopstarter_data/tests.py
coopstarter_data/translation.py
coopstarter_data/views.py
coopstarter_data/fixtures/contributors.json
coopstarter_data/fixtures/countries.json
coopstarter_data/fixtures/fields.json
coopstarter_data/fixtures/format.json
coopstarter_data/fixtures/groups.json
coopstarter_data/fixtures/interfacelanguages.json
coopstarter_data/fixtures/languages.json
coopstarter_data/fixtures/learningoutcomes.json
coopstarter_data/fixtures/organisations.json
coopstarter_data/fixtures/requests.json
coopstarter_data/fixtures/resources.json
coopstarter_data/fixtures/reviews.json
coopstarter_data/fixtures/searcher.json
coopstarter_data/fixtures/sharings.json
coopstarter_data/fixtures/sources.json
coopstarter_data/fixtures/steps.json
coopstarter_data/fixtures/targets.json
coopstarter_data/fixtures/types.json
coopstarter_data/fixtures/users.json
coopstarter_data/migrations/0001_initial.py
coopstarter_data/migrations/0002_auto_20200128_0945.py
coopstarter_data/migrations/0003_auto_20200407_1917.py
coopstarter_data/migrations/0004_auto_20200408_0944.py
coopstarter_data/migrations/0005_auto_20200426_1553.py
coopstarter_data/migrations/0006_interfacelanguage.py
coopstarter_data/migrations/0007_auto_20200513_1552.py
coopstarter_data/migrations/0008_auto_20200521_0950.py
coopstarter_data/migrations/0009_auto_20200525_0851.py
coopstarter_data/migrations/0010_auto_20200525_0910.py
coopstarter_data/migrations/0011_auto_20200603_1823.py
coopstarter_data/migrations/0012_auto_20200630_0910.py
coopstarter_data/migrations/0013_auto_20200701_1431.py
coopstarter_data/migrations/0014_auto_20200705_1320.py
coopstarter_data/migrations/0015_auto_20200709_2230.py
coopstarter_data-0.2.16.dist-info/LICENSE
coopstarter_data-0.2.16.dist-info/METADATA
coopstarter_data-0.2.16.dist-info/WHEEL
coopstarter_data-0.2.16.dist-info/top_level.txt
coopstarter_data-0.2.16.dist-info/RECORD
