Metadata-Version: 2.1
Name: coopstarter-data
Version: 0.2.16
Summary: CoopStarter Application
Home-page: http://git.happy-dev.fr/startinblox/applications/coopstarter/coopstarter-data
Author: Startin'blox
Author-email: benoit@happy-dev.fr
License: MIT
Platform: UNKNOWN
Classifier: Programming Language :: Python :: 3
Requires-Dist: djangoldp (>=2.0.0)
Requires-Dist: djangoldp-conversation (>=2.0.0)
Requires-Dist: djangoldp-account (>=2.0.0)
Requires-Dist: djangoldp-like (>=0.0.0)
Requires-Dist: djangoldp-i18n (>=2.0.0)
Provides-Extra: dev
Requires-Dist: factory-boy (>=2.11.0) ; extra == 'dev'
